{
  "component": {
    "header": {
      "content": {
        "mainMenuToggle": {
          "label": "in praise of folly"
        },
        "logo": {
          "type": "icon"
        }
      }
    },
    "footer": {
      "content": {
        "copyright": {
          "copy": "All rights reserved"
        },
        "sections": [
          {
            "items": [
              {
                "routerLink": "/home",
                "copy": "Home"
              },
              {
                "routerLink": "/about",
                "copy": "About"
              },
              {
                "routerLink": "/calendar",
                "copy": "Calendar"
              },
              {
                "routerLink": "/contact",
                "copy": "Contact"
              }
            ]
          }
        ],
        "social": {
          "items": [
            {
              "type": "facebook",
              "href": "https://www.facebook.com/inpraiseoffolly/"
            },
            {
              "type": "instagram",
              "href": "https://www.instagram.com/inpraiseoffolly/"
            }
          ]
        }
      }
    },
    "mainMenu": {
      "config": {
      },
      "content": {
        "header": {
          "defaultBackText": "Close"
        },
        "items": [
          {
            "style": "link",
            "text": "Home",
            "href": "/home"
          },
          {
            "style": "link",
            "text": "About",
            "href": "/about"
          },
          {
            "style": "link",
            "text": "Calendar",
            "href": "/calendar"
          },
          {
            "style": "link",
            "text": "Contact",
            "href": "/contact"
          }
        ]
      }
    }
  }
}